[
  {
    "rank": 1,
    "bib": 13,
    "fis_code": "510109",
    "name": "HEINZER Franz",
    "year_birth": null,
    "country_code": "SUI",
    "time_raw": "1:56.04",
    "diff_raw": "0.00",
    "distance": 3312.0,
    "points": 0.0,
    "ski": "HE"
  },
  {
    "rank": 2,
    "bib": 8,
    "fis_code": "530194",
    "name": "KITT A.J.",
    "year_birth": null,
    "country_code": "USA",
    "time_raw": "1:56.39",
    "diff_raw": "+0.35",
    "distance": 3312.0,
    "points": 3.23,
    "ski": "HE"
  },
  {
    "rank": 3,
    "bib": 10,
    "fis_code": "50144",
    "name": "ORTLIEB Patrick",
    "year_birth": null,
    "country_code": "AUT",
    "time_raw": "1:56.63",
    "diff_raw": "+0.59",
    "distance": 3312.0,
    "points": 5.44,
    "ski": "HE"
  },
  {
    "rank": 4,
    "bib": 9,
    "fis_code": "510086",
    "name": "GIGANDET Xavier",
    "year_birth": null,
    "country_code": "SUI",
    "time_raw": "1:56.71",
    "diff_raw": "+0.67",
    "distance": 3312.0,
    "points": 6.18,
    "ski": "AT"
  },
  {
    "rank": 4,
    "bib": 11,
    "fis_code": "050091",
    "name": "HOEFLEHNER Helmut",
    "year_birth": null,
    "country_code": "AUT",
    "time_raw": "1:56.71",
    "diff_raw": "+0.67",
    "distance": 3312.0,
    "points": 6.18,
    "ski": "HE"
  },
  {
    "rank": 6,
    "bib": 3,
    "fis_code": "510154",
    "name": "MAHRER Daniel",
    "year_birth": null,
    "country_code": "SUI",
    "time_raw": "1:56.96",
    "diff_raw": "+0.92",
    "distance": 3312.0,
    "points": 8.48,
    "ski": "SA"
  },
  {
    "rank": 7,
    "bib": 16,
    "fis_code": "050127",
    "name": "MADER Guenther",
    "year_birth": null,
    "country_code": "AUT",
    "time_raw": "1:57.02",
    "diff_raw": "+0.98",
    "distance": 3312.0,
    "points": 9.04,
    "ski": "HE"
  },
  {
    "rank": 8,
    "bib": 42,
    "fis_code": "190120",
    "name": "DUVILLARD Adrien",
    "year_birth": null,
    "country_code": "FRA",
    "time_raw": "1:57.09",
    "diff_raw": "+1.05",
    "distance": 3312.0,
    "points": 9.68,
    "ski": "SA"
  },
  {
    "rank": 9,
    "bib": 1,
    "fis_code": "420205",
    "name": "THORSEN Jan Einar",
    "year_birth": null,
    "country_code": "NOR",
    "time_raw": "1:57.16",
    "diff_raw": "+1.12",
    "distance": 3312.0,
    "points": 10.33,
    "ski": "DY"
  },
  {
    "rank": 10,
    "bib": 14,
    "fis_code": "200367",
    "name": "WASMEIER Markus",
    "year_birth": null,
    "country_code": "GER",
    "time_raw": "1:57.17",
    "diff_raw": "+1.13",
    "distance": 3312.0,
    "points": 10.42,
    "ski": "RE"
  },
  {
    "rank": 11,
    "bib": 11,
    "fis_code": "510029",
    "name": "BESSE William",
    "year_birth": null,
    "country_code": "SUI",
    "time_raw": "1:57.25",
    "diff_raw": "+1.21",
    "distance": 3312.0,
    "points": 11.16,
    "ski": "SA"
  },
  {
    "rank": 12,
    "bib": 4,
    "fis_code": "420007",
    "name": "ARNESEN Lasse",
    "year_birth": null,
    "country_code": "NOR",
    "time_raw": "1:57.29",
    "diff_raw": "+1.25",
    "distance": 3312.0,
    "points": 11.53,
    "ski": "DY"
  },
  {
    "rank": 13,
    "bib": 38,
    "fis_code": "290320",
    "name": "MAIR Michael",
    "year_birth": null,
    "country_code": "ITA",
    "time_raw": "1:57.31",
    "diff_raw": "+1.27",
    "distance": 3312.0,
    "points": 11.71,
    "ski": "FI"
  },
  {
    "rank": 14,
    "bib": 7,
    "fis_code": "050239",
    "name": "WIRNSBERGER Peter I",
    "year_birth": null,
    "country_code": "AUT",
    "time_raw": "1:57.41",
    "diff_raw": "+1.37",
    "distance": 3312.0,
    "points": 12.63,
    "ski": "FI"
  },
  {
    "rank": 15,
    "bib": 46,
    "fis_code": "050240",
    "name": "WIRNSBERGER Peter Ii",
    "year_birth": null,
    "country_code": "AUT",
    "time_raw": "1:57.42",
    "diff_raw": "+1.38",
    "distance": 3312.0,
    "points": 12.72,
    "ski": "FI"
  },
  {
    "rank": 16,
    "bib": 2,
    "fis_code": "050199",
    "name": "STOCK Leonard",
    "year_birth": null,
    "country_code": "AUT",
    "time_raw": "1:57.47",
    "diff_raw": "+1.43",
    "distance": 3312.0,
    "points": 13.19,
    "ski": "AT"
  },
  {
    "rank": 17,
    "bib": 34,
    "fis_code": "050186",
    "name": "SIMONLEHNER Bernd",
    "year_birth": null,
    "country_code": "AUT",
    "time_raw": "1:57.51",
    "diff_raw": "+1.47",
    "distance": 3312.0,
    "points": 13.55,
    "ski": "AT"
  },
  {
    "rank": 18,
    "bib": 43,
    "fis_code": "100354",
    "name": "MULLEN Cary",
    "year_birth": null,
    "country_code": "CAN",
    "time_raw": "1:57.59",
    "diff_raw": "+1.55",
    "distance": 3312.0,
    "points": 14.29,
    "ski": "AT"
  },
  {
    "rank": 19,
    "bib": 13,
    "fis_code": "290255",
    "name": "GHEDINA Kristian",
    "year_birth": null,
    "country_code": "ITA",
    "time_raw": "1:57.62",
    "diff_raw": "+1.58",
    "distance": 3312.0,
    "points": 14.57,
    "ski": "FI"
  },
  {
    "rank": 20,
    "bib": 35,
    "fis_code": "100017",
    "name": "BELCZYK Felix",
    "year_birth": null,
    "country_code": "CAN",
    "time_raw": "1:57.65",
    "diff_raw": "+1.61",
    "distance": 3312.0,
    "points": 14.85,
    "ski": "HE"
  },
  {
    "rank": 21,
    "bib": 40,
    "fis_code": "050024",
    "name": "EBERHARTER Stefan",
    "year_birth": null,
    "country_code": "AUT",
    "time_raw": "1:57.71",
    "diff_raw": "+1.67",
    "distance": 3312.0,
    "points": 15.4,
    "ski": "AT"
  },
  {
    "rank": 22,
    "bib": 29,
    "fis_code": "510313",
    "name": "LEHMANN Urs",
    "year_birth": null,
    "country_code": "SUI",
    "time_raw": "1:57.75",
    "diff_raw": "+1.71",
    "distance": 3312.0,
    "points": 15.77,
    "ski": "SA"
  },
  {
    "rank": 23,
    "bib": 44,
    "fis_code": "050072",
    "name": "HAAS Michael",
    "year_birth": null,
    "country_code": "AUT",
    "time_raw": "1:57.78",
    "diff_raw": "+1.74",
    "distance": 3312.0,
    "points": 16.04,
    "ski": "AT"
  },
  {
    "rank": 23,
    "bib": 32,
    "fis_code": "290573",
    "name": "VITALINI Pietro",
    "year_birth": null,
    "country_code": "ITA",
    "time_raw": "1:57.78",
    "diff_raw": "+1.74",
    "distance": 3312.0,
    "points": 16.04,
    "ski": "FI"
  },
  {
    "rank": 25,
    "bib": 31,
    "fis_code": "510069",
    "name": "FAHNER Bernhard",
    "year_birth": null,
    "country_code": "SUI",
    "time_raw": "1:57.91",
    "diff_raw": "+1.87",
    "distance": 3312.0,
    "points": 17.24,
    "ski": "SA"
  },
  {
    "rank": 26,
    "bib": 39,
    "fis_code": "290716",
    "name": "MARTIN Gianfranco",
    "year_birth": null,
    "country_code": "ITA",
    "time_raw": "1:57.94",
    "diff_raw": "+1.90",
    "distance": 3312.0,
    "points": 17.52,
    "ski": "FI"
  },
  {
    "rank": 27,
    "bib": 19,
    "fis_code": "510173",
    "name": "MUELLER Peter",
    "year_birth": null,
    "country_code": "SUI",
    "time_raw": "1:58.04",
    "diff_raw": "+2.00",
    "distance": 3312.0,
    "points": 18.44,
    "ski": "HE"
  },
  {
    "rank": 28,
    "bib": 22,
    "fis_code": "290485",
    "name": "SBARDELLOTTO Danilo",
    "year_birth": null,
    "country_code": "ITA",
    "time_raw": "1:58.12",
    "diff_raw": "+2.08",
    "distance": 3312.0,
    "points": 19.18,
    "ski": "FI"
  },
  {
    "rank": 29,
    "bib": 17,
    "fis_code": "360002",
    "name": "GIRARDELLI Marc",
    "year_birth": null,
    "country_code": "LUX",
    "time_raw": "1:58.16",
    "diff_raw": "+2.12",
    "distance": 3312.0,
    "points": 19.55,
    "ski": "DY"
  },
  {
    "rank": 30,
    "bib": 18,
    "fis_code": "510001",
    "name": "ACCOLA Paul",
    "year_birth": null,
    "country_code": "SUI",
    "time_raw": "1:58.26",
    "diff_raw": "+2.22",
    "distance": 3312.0,
    "points": 20.47,
    "ski": "SA"
  },
  {
    "rank": 31,
    "bib": 26,
    "fis_code": "290791",
    "name": "COLTURI Franco",
    "year_birth": null,
    "country_code": "ITA",
    "time_raw": "1:58.32",
    "diff_raw": "+2.28",
    "distance": 3312.0,
    "points": 21.02,
    "ski": "FI"
  },
  {
    "rank": 32,
    "bib": 45,
    "fis_code": "530284",
    "name": "OLSON Jeff",
    "year_birth": null,
    "country_code": "USA",
    "time_raw": "1:58.41",
    "diff_raw": "+2.37",
    "distance": 3312.0,
    "points": 21.85,
    "ski": "HE"
  },
  {
    "rank": 33,
    "bib": 27,
    "fis_code": "530084",
    "name": "CRIST Reggie",
    "year_birth": null,
    "country_code": "USA",
    "time_raw": "1:58.45",
    "diff_raw": "+2.41",
    "distance": 3312.0,
    "points": 22.22,
    "ski": "HE"
  },
  {
    "rank": 34,
    "bib": 23,
    "fis_code": "190274",
    "name": "PLE Christophe",
    "year_birth": null,
    "country_code": "FRA",
    "time_raw": "1:58.55",
    "diff_raw": "+2.51",
    "distance": 3312.0,
    "points": 23.14,
    "ski": "SA"
  },
  {
    "rank": 35,
    "bib": 15,
    "fis_code": "200392",
    "name": "ZEHENTNER Hannes",
    "year_birth": null,
    "country_code": "GER",
    "time_raw": "1:58.58",
    "diff_raw": "+2.54",
    "distance": 3312.0,
    "points": 23.42,
    "ski": "RE"
  },
  {
    "rank": 36,
    "bib": 37,
    "fis_code": "190138",
    "name": "FINANCE Lionel",
    "year_birth": null,
    "country_code": "FRA",
    "time_raw": "1:58.59",
    "diff_raw": "+2.55",
    "distance": 3312.0,
    "points": 23.51,
    "ski": "SA"
  },
  {
    "rank": 37,
    "bib": 36,
    "fis_code": "290397",
    "name": "PERATHONER Lukas",
    "year_birth": null,
    "country_code": "ITA",
    "time_raw": "1:58.89",
    "diff_raw": "+2.85",
    "distance": 3312.0,
    "points": 26.28,
    "ski": "FI"
  },
  {
    "rank": 38,
    "bib": 52,
    "fis_code": "290426",
    "name": "POLIG Josef",
    "year_birth": null,
    "country_code": "ITA",
    "time_raw": "1:58.95",
    "diff_raw": "+2.91",
    "distance": 3312.0,
    "points": 26.83,
    "ski": "FI"
  },
  {
    "rank": 39,
    "bib": 25,
    "fis_code": "100465",
    "name": "PODIVINSKY Ed",
    "year_birth": null,
    "country_code": "CAN",
    "time_raw": "1:59.06",
    "diff_raw": "+3.02",
    "distance": 3312.0,
    "points": 27.85,
    "ski": "HE"
  },
  {
    "rank": 40,
    "bib": 24,
    "fis_code": "220014",
    "name": "DUNCAN Ronald",
    "year_birth": null,
    "country_code": "GBR",
    "time_raw": "1:59.10",
    "diff_raw": "+3.06",
    "distance": 3312.0,
    "points": 28.22,
    "ski": "HE"
  },
  {
    "rank": 41,
    "bib": 49,
    "fis_code": "420129",
    "name": "LINBERG Asgeir",
    "year_birth": null,
    "country_code": "NOR",
    "time_raw": "1:59.15",
    "diff_raw": "+3.11",
    "distance": 3312.0,
    "points": 28.68,
    "ski": "DY"
  },
  {
    "rank": 42,
    "bib": 48,
    "fis_code": "480082",
    "name": "ANDREEV Vitalij",
    "year_birth": null,
    "country_code": "SOV",
    "time_raw": "1:59.23",
    "diff_raw": "+3.19",
    "distance": 3312.0,
    "points": 29.41,
    "ski": null
  },
  {
    "rank": 43,
    "bib": 21,
    "fis_code": "190140",
    "name": "FIVEL Christophe",
    "year_birth": null,
    "country_code": "FRA",
    "time_raw": "1:59.31",
    "diff_raw": "+3.27",
    "distance": 3312.0,
    "points": 30.15,
    "ski": "SA"
  },
  {
    "rank": 44,
    "bib": 12,
    "fis_code": "200340",
    "name": "TAUSCHER Hansjoerg",
    "year_birth": null,
    "country_code": "GER",
    "time_raw": "1:59.42",
    "diff_raw": "+3.38",
    "distance": 3312.0,
    "points": 31.17,
    "ski": "RE"
  },
  {
    "rank": 45,
    "bib": 58,
    "fis_code": "050318",
    "name": "TEPPAN Franz",
    "year_birth": null,
    "country_code": "AUT",
    "time_raw": "1:59.43",
    "diff_raw": "+3.39",
    "distance": 3312.0,
    "points": 31.26,
    "ski": "AT"
  },
  {
    "rank": 46,
    "bib": 47,
    "fis_code": "480078",
    "name": "CHISTIAKOV Kostantin",
    "year_birth": null,
    "country_code": "SOV",
    "time_raw": "1:59.46",
    "diff_raw": "+3.42",
    "distance": 3312.0,
    "points": 31.54,
    "ski": null
  },
  {
    "rank": 47,
    "bib": 59,
    "fis_code": "420261",
    "name": "HAUGEN Jostein",
    "year_birth": null,
    "country_code": "NOR",
    "time_raw": "1:59.50",
    "diff_raw": "+3.46",
    "distance": 3312.0,
    "points": 31.9,
    "ski": "DY"
  },
  {
    "rank": 48,
    "bib": 50,
    "fis_code": "040023",
    "name": "LEE Steven",
    "year_birth": null,
    "country_code": "AUS",
    "time_raw": "1:59.58",
    "diff_raw": "+3.54",
    "distance": 3312.0,
    "points": 32.64,
    "ski": "FI"
  },
  {
    "rank": 49,
    "bib": 53,
    "fis_code": "050209",
    "name": "STROLZ Hubert",
    "year_birth": null,
    "country_code": "AUT",
    "time_raw": "1:59.70",
    "diff_raw": "+3.66",
    "distance": 3312.0,
    "points": 33.75,
    "ski": "AT"
  },
  {
    "rank": 50,
    "bib": 51,
    "fis_code": "290117",
    "name": "CATTANEO Luca",
    "year_birth": null,
    "country_code": "ITA",
    "time_raw": "2:00.09",
    "diff_raw": "+4.05",
    "distance": 3312.0,
    "points": 37.34,
    "ski": "FI"
  },
  {
    "rank": 51,
    "bib": 60,
    "fis_code": "510145",
    "name": "LOCHER Steve",
    "year_birth": null,
    "country_code": "SUI",
    "time_raw": "2:00.18",
    "diff_raw": "+4.14",
    "distance": 3312.0,
    "points": 38.17,
    "ski": "SA"
  },
  {
    "rank": 52,
    "bib": 54,
    "fis_code": "050171",
    "name": "SALZGEBER Rainer",
    "year_birth": null,
    "country_code": "AUT",
    "time_raw": "2:00.19",
    "diff_raw": "+4.15",
    "distance": 3312.0,
    "points": 38.27,
    "ski": "HE"
  }
]
